[
    {
        "uid": 1,
        "roleset_id": "allow.01",
        "roleset_name": "let",
        "roles": [
            {
                "n": "0",
                "descr": "allower"
            },
            {
                "n": "1",
                "descr": "action allowed"
            }
        ]
    },
    {
        "uid": 2,
        "roleset_id": "allow.02",
        "roleset_name": "allocate",
        "roles": [
            {
                "n": "0",
                "descr": "allocator"
            },
            {
                "n": "1",
                "descr": "thing allocated (us. time)"
            },
            {
                "n": "2",
                "descr": "to some task"
            }
        ]
    },
    {
        "uid": 3,
        "roleset_id": "allow.03",
        "roleset_name": "admit truth of proposition",
        "roles": [
            {
                "n": "0",
                "descr": "admitter"
            },
            {
                "n": "1",
                "descr": "true proposition"
            }
        ]
    },
    {
        "uid": 4,
        "roleset_id": "allowable.04",
        "roleset_name": "permissable",
        "roles": [
            {
                "n": "0",
                "descr": "allower"
            },
            {
                "n": "1",
                "descr": "action allowed (may require concatenation)"
            }
        ]
    }
]