[
    {
        "uid": 1,
        "roleset_id": "avail.01",
        "roleset_name": "provide, often 'take advantage of'",
        "roles": [
            {
                "n": "0",
                "descr": "one providing, taking advantage, includes causes"
            },
            {
                "n": "1",
                "descr": "recipient"
            },
            {
                "n": "2",
                "descr": "thing provided, taken advantage of"
            }
        ]
    },
    {
        "uid": 2,
        "roleset_id": "available.02",
        "roleset_name": "ready for use",
        "roles": [
            {
                "n": "1",
                "descr": "available to whom/what? entity having access to arg2"
            },
            {
                "n": "2",
                "descr": "thing that is available"
            }
        ]
    }
]