[
  {
    "uid": 1,
    "roleset_id": "bandy_about.01",
    "roleset_name": "discuss casually",
    "roles": [
      {
        "n": "0",
        "descr": "discusser(s), agent",
        "descr_trans": "讨论者、代理人"
      },
      {
        "n": "1",
        "descr": "topic",
        "descr_trans": "话题"
      }
    ],
    "roleset_name_trans": "随意讨论"
  },
  {
    "uid": 2,
    "roleset_id": "bandy_around.02",
    "roleset_name": "discuss casually",
    "roles": [
      {
        "n": "0",
        "descr": "discusser/agent(s)",
        "descr_trans": "讨论者/代理人"
      },
      {
        "n": "1",
        "descr": "topic",
        "descr_trans": "话题"
      }
    ],
    "roleset_name_trans": "随意讨论"
  }
]