[
    {
        "uid": 1,
        "roleset_id": "burglarize.01",
        "roleset_name": "steal from",
        "roles": [
            {
                "n": "0",
                "descr": "thief, burglar"
            },
            {
                "n": "1",
                "descr": "thing/place stolen from"
            }
        ]
    },
    {
        "uid": 2,
        "roleset_id": "burgle.02",
        "roleset_name": "to engage in or commit robbery",
        "roles": [
            {
                "n": "0",
                "descr": "robber, thief"
            },
            {
                "n": "1",
                "descr": "person, entity burgled"
            },
            {
                "n": "2",
                "descr": "money or valuables, thing taken"
            }
        ]
    }
]