[
    {
        "uid": 1,
        "roleset_id": "circumscribe.01",
        "roleset_name": "set/define limits, confine",
        "roles": [
            {
                "n": "0",
                "descr": "agent, entity imposing limits"
            },
            {
                "n": "1",
                "descr": "thing limited, confined"
            },
            {
                "n": "2",
                "descr": "mention of limit on arg1, confined to what?"
            }
        ]
    }
]