[
    {
        "uid": 1,
        "roleset_id": "clam.01",
        "roleset_name": "to gather clams",
        "roles": [
            {
                "n": "0",
                "descr": "agent or causer"
            },
            {
                "n": "1",
                "descr": "entity gathered"
            },
            {
                "n": "2",
                "descr": "gathered into"
            },
            {
                "n": "3",
                "descr": "beneficiary"
            }
        ]
    }
]