[
    {
        "uid": 1,
        "roleset_id": "drool.01",
        "roleset_name": "emit saliva",
        "roles": [
            {
                "n": "0",
                "descr": "drooler"
            },
            {
                "n": "1",
                "descr": "drool (cognate object)"
            },
            {
                "n": "2",
                "descr": "destination of drool"
            }
        ]
    },
    {
        "uid": 2,
        "roleset_id": "drool.02",
        "roleset_name": "lust after heartily",
        "roles": [
            {
                "n": "0",
                "descr": "drooler"
            },
            {
                "n": "1",
                "descr": "thing lusted after"
            }
        ]
    }
]