[
  {
    "uid": 1,
    "roleset_id": "duodenojejunostomy.01",
    "roleset_name": "surgery that creates an artificial connection between the duodenum and the jejunum",
    "roles": [
      {
        "n": "0",
        "descr": "agent",
        "descr_trans": "代理人"
      },
      {
        "n": "1",
        "descr": "patient",
        "descr_trans": "病人"
      },
      {
        "n": "2",
        "descr": "product/result",
        "descr_trans": "产品/结果"
      },
      {
        "n": "3",
        "descr": "which part(s) of the bowel is used",
        "descr_trans": "使用肠道的哪一部分"
      }
    ],
    "roleset_name_trans": "在十二指肠和空肠之间建立人工连接的手术"
  }
]