[
    {
        "uid": 1,
        "roleset_id": "employ.01",
        "roleset_name": "pay for working, have a job",
        "roles": [
            {
                "n": "0",
                "descr": "employer"
            },
            {
                "n": "1",
                "descr": "employee"
            },
            {
                "n": "2",
                "descr": "job"
            }
        ]
    },
    {
        "uid": 2,
        "roleset_id": "employ.02",
        "roleset_name": "use",
        "roles": [
            {
                "n": "0",
                "descr": "user"
            },
            {
                "n": "1",
                "descr": "used"
            },
            {
                "n": "2",
                "descr": "job, purpose"
            }
        ]
    }
]