[
    {
        "uid": 1,
        "roleset_id": "escort.01",
        "roleset_name": "go along with",
        "roles": [
            {
                "n": "0",
                "descr": "subject accompanier"
            },
            {
                "n": "1",
                "descr": "object accompanied"
            },
            {
                "n": "3",
                "descr": "start point"
            },
            {
                "n": "4",
                "descr": "end point"
            }
        ]
    }
]