[
    {
        "uid": 1,
        "roleset_id": "execute.01",
        "roleset_name": "kill",
        "roles": [
            {
                "n": "0",
                "descr": "killer"
            },
            {
                "n": "1",
                "descr": "corpse"
            },
            {
                "n": "2",
                "descr": "instrument"
            }
        ]
    },
    {
        "uid": 2,
        "roleset_id": "execute.02",
        "roleset_name": "enact",
        "roles": [
            {
                "n": "0",
                "descr": "agent, doer"
            },
            {
                "n": "1",
                "descr": "thing done"
            },
            {
                "n": "2",
                "descr": "benefactive, done for or about"
            },
            {
                "n": "3",
                "descr": "instrumental"
            }
        ]
    }
]