[
    {
        "uid": 1,
        "roleset_id": "fit.01",
        "roleset_name": "CAUSE TO fit",
        "roles": [
            {
                "n": "0",
                "descr": "agent, causer of fitting; must be present for this sense to apply"
            },
            {
                "n": "1",
                "descr": "thing that fits"
            },
            {
                "n": "2",
                "descr": "fits whom, what, where"
            }
        ]
    },
    {
        "uid": 2,
        "roleset_id": "fit.03",
        "roleset_name": "ready, primed",
        "roles": [
            {
                "n": "1",
                "descr": "entity who is primed, ready"
            },
            {
                "n": "2",
                "descr": "to what"
            }
        ]
    },
    {
        "uid": 3,
        "roleset_id": "fit.04",
        "roleset_name": "have a paroxysm",
        "roles": [
            {
                "n": "1",
                "descr": "experiencer"
            },
            {
                "n": "2",
                "descr": "type or nature of attack"
            }
        ]
    },
    {
        "uid": 4,
        "roleset_id": "fit.05",
        "roleset_name": "in good physical condition; healthy and athletic",
        "roles": [
            {
                "n": "1",
                "descr": "healthy one"
            }
        ]
    },
    {
        "uid": 5,
        "roleset_id": "fit.06",
        "roleset_name": "be the right size; stative sense",
        "roles": [
            {
                "n": "1",
                "descr": "thing that fits"
            },
            {
                "n": "2",
                "descr": "fits what, where"
            }
        ]
    },
    {
        "uid": 6,
        "roleset_id": "fit_in.02",
        "roleset_name": "fit in a specific place due to suitable features",
        "roles": [
            {
                "n": "1",
                "descr": "first or all things fitting in"
            },
            {
                "n": "2",
                "descr": "second thing, fitting in with what"
            }
        ]
    }
]