[
    {
        "uid": 1,
        "roleset_id": "incept.01",
        "roleset_name": "beginning, origination",
        "roles": [
            {
                "n": "0",
                "descr": "agent (probably rare)"
            },
            {
                "n": "1",
                "descr": "thing originating"
            },
            {
                "n": "2",
                "descr": "inception as what"
            }
        ]
    },
    {
        "uid": 2,
        "roleset_id": "incept.02",
        "roleset_name": "graduate from a university",
        "roles": [
            {
                "n": "0",
                "descr": "student"
            },
            {
                "n": "1",
                "descr": "learning institution"
            },
            {
                "n": "2",
                "descr": "with which degree"
            }
        ]
    }
]