[
    {
        "uid": 1,
        "roleset_id": "lash.01",
        "roleset_name": "to tie",
        "roles": [
            {
                "n": "0",
                "descr": "tier, agent"
            },
            {
                "n": "1",
                "descr": "entity lashed"
            },
            {
                "n": "2",
                "descr": "entity lashed to"
            }
        ]
    },
    {
        "uid": 2,
        "roleset_id": "lash_out.02",
        "roleset_name": "to attack verbally",
        "roles": [
            {
                "n": "0",
                "descr": "attacker, agent"
            },
            {
                "n": "1",
                "descr": "lash at"
            }
        ]
    }
]