[
    {
        "uid": 1,
        "roleset_id": "low.01",
        "roleset_name": "make the characteristic noise of a cow",
        "roles": [
            {
                "n": "0",
                "descr": "low-er"
            }
        ]
    },
    {
        "uid": 2,
        "roleset_id": "low.02",
        "roleset_name": "be depressed, in poor spirits",
        "roles": [
            {
                "n": "0",
                "descr": "cause of depression"
            },
            {
                "n": "1",
                "descr": "entity in low spirits"
            }
        ]
    },
    {
        "uid": 3,
        "roleset_id": "low.03",
        "roleset_name": "be unrefined, base, immoral",
        "roles": [
            {
                "n": "1",
                "descr": "low entity/action (may require concatenation)"
            }
        ]
    },
    {
        "uid": 4,
        "roleset_id": "low.04",
        "roleset_name": "have a location towards the bottom of a framework",
        "roles": [
            {
                "n": "1",
                "descr": "low thing"
            },
            {
                "n": "2",
                "descr": "the lower portion of what, domain"
            },
            {
                "n": "3",
                "descr": "measurment"
            },
            {
                "n": "4",
                "descr": "axis"
            },
            {
                "n": "5",
                "descr": "scale"
            },
            {
                "n": "6",
                "descr": "anchor"
            }
        ]
    },
    {
        "uid": 5,
        "roleset_id": "lower.05",
        "roleset_name": "cause to go down, esp of financial usage, decreasing",
        "roles": [
            {
                "n": "0",
                "descr": "entity moving something downward"
            },
            {
                "n": "1",
                "descr": "Logical subject, patient, thing going down"
            },
            {
                "n": "2",
                "descr": "EXT, amount gone down by"
            },
            {
                "n": "3",
                "descr": "start point"
            },
            {
                "n": "4",
                "descr": "end point, end state of arg1"
            },
            {
                "n": "5",
                "descr": "anchor"
            },
            {
                "n": "6",
                "descr": "axis"
            }
        ]
    }
]