[
  {
    "uid": 1,
    "roleset_id": "modulate.01",
    "roleset_name": "change, modify",
    "roles": [
      {
        "n": "0",
        "descr": "composer",
        "descr_trans": "作曲家"
      },
      {
        "n": "1",
        "descr": "music",
        "descr_trans": "音乐"
      },
      {
        "n": "2",
        "descr": "from",
        "descr_trans": "从"
      },
      {
        "n": "3",
        "descr": "to",
        "descr_trans": "到"
      }
    ],
    "roleset_name_trans": "改变，修改"
  }
]