[
    {
        "uid": 1,
        "roleset_id": "patent.01",
        "roleset_name": "to obtain a patent for",
        "roles": [
            {
                "n": "0",
                "descr": "holder of patent"
            },
            {
                "n": "1",
                "descr": "invention"
            },
            {
                "n": "2",
                "descr": "inventor, if separate from arg0"
            }
        ]
    },
    {
        "uid": 2,
        "roleset_id": "patent.02",
        "roleset_name": "be free or clear of, open",
        "roles": [
            {
                "n": "1",
                "descr": "entity that is free of debris"
            }
        ]
    }
]