[
  {
    "uid": 1,
    "roleset_id": "pomade.01",
    "roleset_name": "cover with pomade",
    "roles": [
      {
        "n": "0",
        "descr": "applier of pomade, agent",
        "descr_trans": "润发油涂抹者、涂抹剂"
      },
      {
        "n": "1",
        "descr": "hair, surface pomaded",
        "descr_trans": "头发，表面涂有润发油"
      },
      {
        "n": "2",
        "descr": "pomade itself, type of pomade",
        "descr_trans": "润发油本身，润发油的类型"
      }
    ],
    "roleset_name_trans": "涂上润发油"
  }
]