[
  {
    "uid": 1,
    "roleset_id": "preadapt.01",
    "roleset_name": "adapt in advance",
    "roles": [
      {
        "n": "0",
        "descr": "agent, adaptor",
        "descr_trans": "代理、适配器"
      },
      {
        "n": "1",
        "descr": "thing adapted",
        "descr_trans": "适应的东西"
      },
      {
        "n": "2",
        "descr": "adapted to",
        "descr_trans": "适应"
      },
      {
        "n": "3",
        "descr": "adapted from",
        "descr_trans": "改编自"
      }
    ],
    "roleset_name_trans": "提前适应"
  }
]