[
  {
    "uid": 1,
    "roleset_id": "precondition.01",
    "roleset_name": "stipulation prior to an agreement",
    "roles": [
      {
        "n": "0",
        "descr": "causer of stipulation, agent",
        "descr_trans": "规定的起因、代理人"
      },
      {
        "n": "1",
        "descr": "stipulation",
        "descr_trans": "规定"
      },
      {
        "n": "2",
        "descr": "purpose of condition",
        "descr_trans": "条件的目的"
      }
    ],
    "roleset_name_trans": "协议之前的约定"
  },
  {
    "uid": 2,
    "roleset_id": "precondition.02",
    "roleset_name": "cause to be in the required         condition beforehand",
    "roles": [
      {
        "n": "0",
        "descr": "agent; causer of conditioning",
        "descr_trans": "代理人;调理的原因"
      },
      {
        "n": "1",
        "descr": "entity conditioned",
        "descr_trans": "实体条件"
      },
      {
        "n": "2",
        "descr": "topic, preconditioned to, for, or about",
        "descr_trans": "主题，以、为或关于为条件"
      }
    ],
    "roleset_name_trans": "使事先处于所需的状态"
  }
]