[
    {
        "uid": 1,
        "roleset_id": "precede.01",
        "roleset_name": "go before",
        "roles": [
            {
                "n": "0",
                "descr": "causal agent"
            },
            {
                "n": "1",
                "descr": "thing preceding (thing that comes first)"
            },
            {
                "n": "2",
                "descr": "thing preceded (thing that comes second)"
            },
            {
                "n": "3",
                "descr": "domain in which priority occurs"
            }
        ]
    }
]