[
    {
        "uid": 1,
        "roleset_id": "problematic.01",
        "roleset_name": "constituting a problem",
        "roles": [
            {
                "n": "0",
                "descr": "problematic entity/situation"
            },
            {
                "n": "1",
                "descr": "further description of the nature of the problem"
            },
            {
                "n": "2",
                "descr": "problematic for whom, entity suffering due to problem"
            }
        ]
    }
]