[
    {
        "uid": 1,
        "roleset_id": "reaffix.01",
        "roleset_name": "attach, again",
        "roles": [
            {
                "n": "0",
                "descr": "agent"
            },
            {
                "n": "1",
                "descr": "thing attached"
            },
            {
                "n": "2",
                "descr": "destination arg1 attached to"
            },
            {
                "n": "3",
                "descr": "instrument of bonding, glue"
            }
        ]
    }
]