[
    {
        "uid": 1,
        "roleset_id": "ripen.01",
        "roleset_name": "(make) become ripe, becoming ripe",
        "roles": [
            {
                "n": "0",
                "descr": "causer of ripening"
            },
            {
                "n": "1",
                "descr": "thing becoming ripe"
            }
        ]
    },
    {
        "uid": 2,
        "roleset_id": "ripe.02",
        "roleset_name": "ready, mature",
        "roles": [
            {
                "n": "1",
                "descr": "fruit (or other)"
            },
            {
                "n": "2",
                "descr": "ready for what"
            }
        ]
    }
]