[
    {
        "uid": 1,
        "roleset_id": "saponify.01",
        "roleset_name": "to convert to soap",
        "roles": [
            {
                "n": "0",
                "descr": "soap-maker, agent"
            },
            {
                "n": "1",
                "descr": "entity being converted to soap"
            },
            {
                "n": "2",
                "descr": "Instrument or Manner if separate from arg 0"
            },
            {
                "n": "3",
                "descr": "Soap, result"
            }
        ]
    }
]