[
    {
        "uid": 1,
        "roleset_id": "southbound.07",
        "roleset_name": "headed south",
        "roles": [
            {
                "n": "1",
                "descr": "entity headed south"
            },
            {
                "n": "2",
                "descr": "other explicit destination"
            },
            {
                "n": "3",
                "descr": "anchoring framework"
            },
            {
                "n": "4",
                "descr": "axis, path, trajectory"
            }
        ]
    }
]