[
    {
        "uid": 1,
        "roleset_id": "stimulate.01",
        "roleset_name": "cause an increase (in interest, etc), etc.)",
        "roles": [
            {
                "n": "0",
                "descr": "cause of increase"
            },
            {
                "n": "1",
                "descr": "thing increasing"
            },
            {
                "n": "2",
                "descr": "instrument, if agent also present"
            },
            {
                "n": "3",
                "descr": "end state of arg1"
            }
        ]
    }
]