[
  {
    "uid": 1,
    "roleset_id": "suicidal.01",
    "roleset_name": "inclined to end one's own life",
    "roles": [
      {
        "n": "0",
        "descr": "stimulus",
        "descr_trans": "刺激"
      },
      {
        "n": "1",
        "descr": "suicidal entity",
        "descr_trans": "自杀实体"
      }
    ],
    "roleset_name_trans": "倾向于结束自己的生命"
  },
  {
    "uid": 2,
    "roleset_id": "suicide.02",
    "roleset_name": "end one's own life",
    "roles": [
      {
        "n": "0",
        "descr": "stimulus",
        "descr_trans": "刺激"
      },
      {
        "n": "1",
        "descr": "entity taking own life",
        "descr_trans": "实体自杀"
      }
    ],
    "roleset_name_trans": "结束自己的生命"
  }
]