[
  {
    "uid": 1,
    "roleset_id": "throw.01",
    "roleset_name": "throw, sending through the air, manually, projection of an object through space",
    "roles": [
      {
        "n": "0",
        "descr": "thrower",
        "descr_trans": "投掷者"
      },
      {
        "n": "1",
        "descr": "thing thrown",
        "descr_trans": "扔东西"
      },
      {
        "n": "2",
        "descr": "thrown at, to, over, etc",
        "descr_trans": "扔向、扔向、越过等"
      }
    ],
    "roleset_name_trans": "投掷，通过空气发送，手动，通过空间投射物体"
  },
  {
    "uid": 2,
    "roleset_id": "throw.03",
    "roleset_name": "hold",
    "roles": [
      {
        "n": "0",
        "descr": "holder",
        "descr_trans": "持有者"
      },
      {
        "n": "1",
        "descr": "thing held",
        "descr_trans": "举行的事情"
      }
    ],
    "roleset_name_trans": "抓住"
  },
  {
    "uid": 3,
    "roleset_id": "throw_away.07",
    "roleset_name": "toss, get rid of",
    "roles": [
      {
        "n": "0",
        "descr": "thrower",
        "descr_trans": "投掷者"
      },
      {
        "n": "1",
        "descr": "thing gotten rid of",
        "descr_trans": "东西被摆脱了"
      }
    ],
    "roleset_name_trans": "扔掉，摆脱"
  },
  {
    "uid": 4,
    "roleset_id": "throw_in.02",
    "roleset_name": "include",
    "roles": [
      {
        "n": "0",
        "descr": "agent, entity causing some grouping",
        "descr_trans": "代理，导致某种分组的实体"
      },
      {
        "n": "1",
        "descr": "theme, thing being included in some group",
        "descr_trans": "主题，包含在某个组中的事物"
      },
      {
        "n": "2",
        "descr": "group",
        "descr_trans": "团体"
      }
    ],
    "roleset_name_trans": "包括"
  },
  {
    "uid": 5,
    "roleset_id": "throw_out.04",
    "roleset_name": "say",
    "roles": [
      {
        "n": "0",
        "descr": "Sayer",
        "descr_trans": "赛耶尔"
      },
      {
        "n": "1",
        "descr": "Utterance",
        "descr_trans": "发声"
      },
      {
        "n": "2",
        "descr": "Hearer",
        "descr_trans": "听者"
      }
    ],
    "roleset_name_trans": "说"
  },
  {
    "uid": 6,
    "roleset_id": "throw_out.06",
    "roleset_name": "toss, get rid of",
    "roles": [
      {
        "n": "0",
        "descr": "thrower",
        "descr_trans": "投掷者"
      },
      {
        "n": "1",
        "descr": "thing gotten rid of",
        "descr_trans": "东西被摆脱了"
      }
    ],
    "roleset_name_trans": "扔掉，摆脱"
  },
  {
    "uid": 7,
    "roleset_id": "throw_up.05",
    "roleset_name": "puke with object",
    "roles": [
      {
        "n": "0",
        "descr": "puker",
        "descr_trans": "呕吐"
      },
      {
        "n": "1",
        "descr": "former contents of stomach",
        "descr_trans": "以前的胃内容物"
      }
    ],
    "roleset_name_trans": "用物体呕吐"
  }
]