[
    {
        "uid": 1,
        "roleset_id": "thrum.01",
        "roleset_name": "sound with a monotonous hum",
        "roles": [
            {
                "n": "1",
                "descr": "emitter of sound"
            },
            {
                "n": "2",
                "descr": "location of sound"
            }
        ]
    },
    {
        "uid": 2,
        "roleset_id": "thrum.02",
        "roleset_name": "strum the strings of a stringed instrument",
        "roles": [
            {
                "n": "0",
                "descr": "performer"
            },
            {
                "n": "1",
                "descr": "chords/melody"
            },
            {
                "n": "2",
                "descr": "musical instrument"
            }
        ]
    },
    {
        "uid": 3,
        "roleset_id": "thrum.03",
        "roleset_name": "make a rythmic sound/motion",
        "roles": [
            {
                "n": "0",
                "descr": "causal agent"
            },
            {
                "n": "1",
                "descr": "thing sounding with thrumming"
            },
            {
                "n": "2",
                "descr": "location"
            }
        ]
    }
]