[
    {
        "uid": 1,
        "roleset_id": "titrate.01",
        "roleset_name": "measure the amount of a constituent in a solution",
        "roles": [
            {
                "n": "0",
                "descr": "Measurer (chemist, doctor)"
            },
            {
                "n": "1",
                "descr": "Chemical/Drugs"
            },
            {
                "n": "2",
                "descr": "Starting point before titration"
            },
            {
                "n": "3",
                "descr": "Endpoint after titration"
            }
        ]
    }
]