[
    {
        "uid": 1,
        "roleset_id": "unbearable.01",
        "roleset_name": "not able to be held, endured",
        "roles": [
            {
                "n": "0",
                "descr": "endurer"
            },
            {
                "n": "1",
                "descr": "thing endured"
            },
            {
                "n": "2",
                "descr": "benefactive"
            },
            {
                "n": "3",
                "descr": "secondary predication on arg1"
            }
        ]
    }
]