[
    {
        "uid": 1,
        "roleset_id": "volunteer.01",
        "roleset_name": "to give or offer to give voluntarily",
        "roles": [
            {
                "n": "0",
                "descr": "entity volunteering, voluntary agent"
            },
            {
                "n": "1",
                "descr": "thing offered"
            },
            {
                "n": "2",
                "descr": "recipient"
            }
        ]
    },
    {
        "uid": 2,
        "roleset_id": "voluntary.02",
        "roleset_name": "self-initiated",
        "roles": [
            {
                "n": "0",
                "descr": "entity volunteering, voluntary agent"
            },
            {
                "n": "1",
                "descr": "thing offered"
            },
            {
                "n": "2",
                "descr": "recipient"
            }
        ]
    }
]