[
  {
    "uid": 1,
    "roleset_id": "war.01",
    "roleset_name": "to carry on warfare, wage war",
    "roles": [
      {
        "n": "0",
        "descr": "warmonger, agent",
        "descr_trans": "好战分子、代理人"
      },
      {
        "n": "1",
        "descr": "war against/with, other entity warring with agent.",
        "descr_trans": "与其他实体交战/与其他实体交战。"
      },
      {
        "n": "2",
        "descr": "topic, war over what?",
        "descr_trans": "话题，战争是因为什么？"
      }
    ],
    "roleset_name_trans": "进行战争，发动战争"
  }
]